README
setup.py
./pyrpm/__init__.py
./pyrpm/rpm.py
./pyrpm/rpmdefs.py
pyrpm.egg-info/PKG-INFO
pyrpm.egg-info/SOURCES.txt
pyrpm.egg-info/dependency_links.txt
pyrpm.egg-info/entry_points.txt
pyrpm.egg-info/not-zip-safe
pyrpm.egg-info/requires.txt
pyrpm.egg-info/top_level.txt