Metadata-Version: 1.0
Name: pyrpm
Version: 0.3
Summary: A pure python rpm reader
Home-page: UNKNOWN
Author: Mario Morgado
Author-email: mjvm@caixamagica.pt
License: BSD
Platform: UNKNOWN
